evpsim/__init__.py
evpsim/behavior/__init__.py
evpsim/behavior/base_classes.py
evpsim/behavior/behavior.py
evpsim/behavior/criterion.py
evpsim/behavior/flow.py
evpsim/behavior/genevp.py
evpsim/behavior/isotropic_hardening.py
evpsim/behavior/kinematic_hardening.py
evpsim/behavior/potential.py
evpsim/simulator/__init__.py
evpsim/simulator/material_simulator.py
evpsim/simulator/rotation.py
evpsim/simulator/simulator_load.py
evpsim/tools/__init__.py
evpsim/tools/base_magic.py
evpsim/tools/elasticity_helper.py
evpsim/tools/tenalg.py
evpsim/tools/variables.py
evpsim-0.1.0.dist-info/LICENSE
evpsim-0.1.0.dist-info/METADATA
evpsim-0.1.0.dist-info/WHEEL
evpsim-0.1.0.dist-info/top_level.txt
evpsim-0.1.0.dist-info/RECORD
