Metadata-Version: 2.1
Name: evpsim
Version: 0.1.0
Summary: Python ElastoViscoPlastic mechanical behavior simulator
Home-page: 
Author-email: basile.marchand@gmail.com
Classifier: Development Status :: 4 - Beta
Classifier: Intended Audience :: Education
Classifier: Intended Audience :: Science/Research
Classifier: License :: OSI Approved :: GNU General Public License v3 (GPLv3)
Classifier: Topic :: Scientific/Engineering
License-File: LICENSE
Requires-Dist: numpy
Requires-Dist: scipy
Requires-Dist: matplotlib
Requires-Dist: numba
Provides-Extra: test
Requires-Dist: pytest ; extra == 'test'
